{
  "form_name": "Oregon SEA Application",
  "form_description": "Oregon Self Employment Assistance Program application questions",
  "version": "1.0",
  "sections": [
    {
      "id": 1,
      "name": "business_overview",
      "title": "Business Overview",
      "description": "Define your business concept and goals"
    },
    {
      "id": 2,
      "name": "qualifications",
      "title": "Qualifications & Skills",
      "description": "Your experience and capabilities"
    },
    {
      "id": 3,
      "name": "startup_costs",
      "title": "Startup Costs",
      "description": "Financial planning for launch"
    },
    {
      "id": 4,
      "name": "financial_diligence",
      "title": "Financial Due Diligence",
      "description": "Your financial situation"
    },
    {
      "id": 5,
      "name": "licensing",
      "title": "Licensing and Regulations",
      "description": "Legal requirements"
    },
    {
      "id": 6,
      "name": "market_research",
      "title": "Market Research",
      "description": "Understanding your market"
    },
    {
      "id": 7,
      "name": "marketing",
      "title": "Marketing Analysis",
      "description": "How you'll reach customers"
    },
    {
      "id": 8,
      "name": "competitive",
      "title": "Competitive Analysis",
      "description": "Your competitive position"
    },
    {
      "id": 9,
      "name": "risks",
      "title": "Risks and Challenges",
      "description": "Anticipating and managing challenges"
    }
  ],
  "questions": [
    {
      "id": "1",
      "section_id": 1,
      "question_text": "What is the nature of your business? Detail the products/services that you will be providing.",
      "question_type": "long_text",
      "priority": 1,
      "depends_on": null,
      "helper_text": "Think about: What problem do you solve? Who are you helping? What makes your approach unique?"
    },
    {
      "id": "2a",
      "section_id": 1,
      "question_text": "Have you established a location to conduct your business?",
      "question_type": "yes_no",
      "priority": 2,
      "depends_on": null,
      "helper_text": "Remote work from home is a valid location for tech/consulting businesses"
    },
    {
      "id": "2b",
      "section_id": 1,
      "question_text": "If not, what is the expected date of occupancy?",
      "question_type": "text",
      "priority": 2,
      "depends_on": "2a",
      "helper_text": "Only answer if you said 'No' to 2a"
    },
    {
      "id": "3",
      "section_id": 1,
      "question_text": "Are you free from direction or control of any other entity?",
      "question_type": "yes_no",
      "priority": 1,
      "depends_on": null,
      "helper_text": "This confirms you'll be truly self-employed, not controlled by another company"
    },
    {
      "id": "4",
      "section_id": 1,
      "question_text": "What is your 6-12 month goal? Please include specific information.",
      "question_type": "long_text",
      "priority": 1,
      "depends_on": null,
      "helper_text": "Be specific: number of clients, revenue targets, milestones. Make it measurable."
    },
    {
      "id": "5",
      "section_id": 1,
      "question_text": "What is your 2-3 year goal? Please include specific information.",
      "question_type": "long_text",
      "priority": 2,
      "depends_on": null,
      "helper_text": "Think bigger picture: scaling, reputation, sustainability, income level"
    },
    {
      "id": "6",
      "section_id": 2,
      "question_text": "Describe your qualifications to operate this business successfully (examples: relevant education, certification, previous experience, etc).",
      "question_type": "long_text",
      "priority": 1,
      "depends_on": null,
      "helper_text": "List relevant education, certifications, and work experience. Be specific about skills that directly apply."
    },
    {
      "id": "7a",
      "section_id": 2,
      "question_text": "Have you ever owned a business before?",
      "question_type": "yes_no",
      "priority": 2,
      "depends_on": null,
      "helper_text": null
    },
    {
      "id": "7b",
      "section_id": 2,
      "question_text": "If yes, what type of business?",
      "question_type": "text",
      "priority": 2,
      "depends_on": "7a",
      "helper_text": null
    },
    {
      "id": "8",
      "section_id": 2,
      "question_text": "Do you have any business skills (talents or abilities specific to running a business) that will aid your success in this business?",
      "question_type": "long_text",
      "priority": 2,
      "depends_on": null,
      "helper_text": "Think about: project management, client communication, technical writing, problem-solving, systems thinking"
    },
    {
      "id": "9",
      "section_id": 3,
      "question_text": "What are the estimated startup costs needed to set up this business?",
      "question_type": "number",
      "priority": 1,
      "depends_on": null,
      "helper_text": "Consider: computer equipment, software licenses, website, business registration, insurance, marketing materials"
    },
    {
      "id": "10a",
      "section_id": 3,
      "question_text": "Will you be fully financially responsible for these costs?",
      "question_type": "yes_no",
      "priority": 1,
      "depends_on": null,
      "helper_text": null
    },
    {
      "id": "10b",
      "section_id": 3,
      "question_text": "If not, what amount and percentage will you invest?",
      "question_type": "text",
      "priority": 2,
      "depends_on": "10a",
      "helper_text": null
    },
    {
      "id": "10c",
      "section_id": 3,
      "question_text": "If needed, where will the additional funding come from?",
      "question_type": "text",
      "priority": 2,
      "depends_on": "10a",
      "helper_text": null
    },
    {
      "id": "11a",
      "section_id": 3,
      "question_text": "Have the terms for the financing been finalized?",
      "question_type": "yes_no",
      "priority": 2,
      "depends_on": null,
      "helper_text": null
    },
    {
      "id": "11b",
      "section_id": 3,
      "question_text": "If not, what is the estimated date of completion?",
      "question_type": "text",
      "priority": 2,
      "depends_on": "11a",
      "helper_text": null
    },
    {
      "id": "12",
      "section_id": 4,
      "question_text": "What is your current credit score?",
      "question_type": "number",
      "priority": 2,
      "depends_on": null,
      "helper_text": "If you don't know, check Credit Karma or similar"
    },
    {
      "id": "13a",
      "section_id": 4,
      "question_text": "Have you filed bankruptcy in the last 7 years?",
      "question_type": "yes_no",
      "priority": 2,
      "depends_on": null,
      "helper_text": null
    },
    {
      "id": "13b",
      "section_id": 4,
      "question_text": "If yes, when?",
      "question_type": "text",
      "priority": 2,
      "depends_on": "13a",
      "helper_text": null
    },
    {
      "id": "14",
      "section_id": 4,
      "question_text": "Do you have any personal assets that can be used to secure a loan in the event financing from a financial institution is necessary?",
      "question_type": "yes_no",
      "priority": 2,
      "depends_on": null,
      "helper_text": "This might not be needed for a lean consulting/content business"
    },
    {
      "id": "15",
      "section_id": 4,
      "question_text": "Currently, how much do you contribute, in dollars, to your household expenses?",
      "question_type": "number",
      "priority": 1,
      "depends_on": null,
      "helper_text": "Monthly amount. Be realistic about your living costs."
    },
    {
      "id": "16",
      "section_id": 4,
      "question_text": "What will your estimated business expenses be?",
      "question_type": "number",
      "priority": 1,
      "depends_on": null,
      "helper_text": "Monthly operating costs: software, internet, phone, insurance, marketing, etc."
    },
    {
      "id": "17",
      "section_id": 4,
      "question_text": "To cover your business expenses and financial responsibility to your household, how much product/services will the business need to provide to meet these financial obligations?",
      "question_type": "number",
      "priority": 1,
      "depends_on": null,
      "helper_text": "Total monthly revenue needed = household contribution + business expenses"
    },
    {
      "id": "18",
      "section_id": 4,
      "question_text": "What is your plan should you encounter a shortfall?",
      "question_type": "long_text",
      "priority": 1,
      "depends_on": null,
      "helper_text": "Show you've thought about contingencies: savings, reducing expenses, side projects, etc."
    },
    {
      "id": "19",
      "section_id": 4,
      "question_text": "Have you created a preliminary budget for your business?",
      "question_type": "yes_no",
      "priority": 1,
      "depends_on": null,
      "helper_text": "If not, we should create one!"
    },
    {
      "id": "20a",
      "section_id": 5,
      "question_text": "Is this a new or existing business?",
      "question_type": "choice",
      "priority": 1,
      "depends_on": null,
      "helper_text": "Options: New or Existing"
    },
    {
      "id": "20b",
      "section_id": 5,
      "question_text": "Is it registered with the State of Oregon?",
      "question_type": "yes_no",
      "priority": 2,
      "depends_on": null,
      "helper_text": null
    },
    {
      "id": "20c",
      "section_id": 5,
      "question_text": "If so, what is the Business Registry Number or Business Identification Number (BIN)?",
      "question_type": "text",
      "priority": 2,
      "depends_on": "20b",
      "helper_text": null
    },
    {
      "id": "21a",
      "section_id": 5,
      "question_text": "Have all the required licenses, insurance and certifications been obtained?",
      "question_type": "yes_no",
      "priority": 2,
      "depends_on": null,
      "helper_text": "General business license, professional liability insurance if consulting"
    },
    {
      "id": "21b",
      "section_id": 5,
      "question_text": "If not, what is the estimated date of completion?",
      "question_type": "text",
      "priority": 2,
      "depends_on": "21a",
      "helper_text": null
    },
    {
      "id": "22a",
      "section_id": 6,
      "question_text": "How would you describe the demand for your product/services?",
      "question_type": "long_text",
      "priority": 1,
      "depends_on": null,
      "helper_text": "Research: Are companies hiring for your skills? What's the freelance market like?"
    },
    {
      "id": "22b",
      "section_id": 6,
      "question_text": "How have you determined that your product/services are needed?",
      "question_type": "long_text",
      "priority": 1,
      "depends_on": null,
      "helper_text": "Evidence: job postings, market trends, conversations with potential clients, industry reports"
    },
    {
      "id": "23a",
      "section_id": 6,
      "question_text": "How would you describe your targeted customer?",
      "question_type": "long_text",
      "priority": 1,
      "depends_on": null,
      "helper_text": "Be specific: Industry, company size, technical sophistication, pain points"
    },
    {
      "id": "23b",
      "section_id": 6,
      "question_text": "Where is the targeted market area?",
      "question_type": "text",
      "priority": 1,
      "depends_on": null,
      "helper_text": "Remote work opens this up: Pacific Northwest, US, global?"
    },
    {
      "id": "24",
      "section_id": 6,
      "question_text": "Who will buy your products and services?",
      "question_type": "long_text",
      "priority": 1,
      "depends_on": null,
      "helper_text": "Specific roles: CTOs, engineering managers, startups, dev teams?"
    },
    {
      "id": "25",
      "section_id": 6,
      "question_text": "As a new business, what are some of the barriers that you may encounter?",
      "question_type": "long_text",
      "priority": 1,
      "depends_on": null,
      "helper_text": "Be honest: client acquisition, marketing yourself, pricing, competition, consistency"
    },
    {
      "id": "26",
      "section_id": 6,
      "question_text": "What market research have you done to support the need for your products/services?",
      "question_type": "long_text",
      "priority": 2,
      "depends_on": null,
      "helper_text": "Document what you've learned about the market"
    },
    {
      "id": "27",
      "section_id": 7,
      "question_text": "What marketing tools will you use to market your business?",
      "question_type": "long_text",
      "priority": 1,
      "depends_on": null,
      "helper_text": "Tech blog, LinkedIn, GitHub, tech conferences, networking, word-of-mouth, portfolio site"
    },
    {
      "id": "28a",
      "section_id": 7,
      "question_text": "What is your estimated marketing budget for the next 6 months?",
      "question_type": "number",
      "priority": 2,
      "depends_on": null,
      "helper_text": "Can be modest: website hosting, domain, maybe some sponsored posts or conference tickets"
    },
    {
      "id": "28b",
      "section_id": 7,
      "question_text": "Is this included in your business expenses?",
      "question_type": "yes_no",
      "priority": 2,
      "depends_on": null,
      "helper_text": null
    },
    {
      "id": "29",
      "section_id": 8,
      "question_text": "Provide the names of 3 of your potential competitors or explain a lack of competition.",
      "question_type": "long_text",
      "priority": 1,
      "depends_on": null,
      "helper_text": "Other consultants, agencies, or explain your niche positioning"
    },
    {
      "id": "30",
      "section_id": 8,
      "question_text": "What makes your business competitive within its respective market?",
      "question_type": "long_text",
      "priority": 1,
      "depends_on": null,
      "helper_text": "What unique combination of skills, experience, or approach do you offer?"
    },
    {
      "id": "31",
      "section_id": 8,
      "question_text": "What means will you provide your clients/customers to contact you?",
      "question_type": "text",
      "priority": 2,
      "depends_on": null,
      "helper_text": "Professional email, website contact form, LinkedIn, phone"
    },
    {
      "id": "32",
      "section_id": 8,
      "question_text": "How much control will you have over the operation of the business and how/products/services are delivered?",
      "question_type": "long_text",
      "priority": 2,
      "depends_on": null,
      "helper_text": "Full control: you set rates, choose clients, define scope, manage deliverables"
    },
    {
      "id": "33",
      "section_id": 8,
      "question_text": "Provide 3 milestones that will indicate your business is on the path to success",
      "question_type": "long_text",
      "priority": 1,
      "depends_on": null,
      "helper_text": "Examples: First paying client, first repeat client, positive cash flow, published articles with engagement"
    },
    {
      "id": "34a",
      "section_id": 9,
      "question_text": "As a new business owner, what are some of the personal or business challenges you may encounter?",
      "question_type": "long_text",
      "priority": 1,
      "depends_on": null,
      "helper_text": "Be thoughtful: irregular income, self-motivation, isolation, imposter syndrome, client acquisition"
    },
    {
      "id": "34b",
      "section_id": 9,
      "question_text": "How will you attempt to address/prevent these challenges?",
      "question_type": "long_text",
      "priority": 1,
      "depends_on": null,
      "helper_text": "Show your strategies: routines, support systems, tools, accountability, community"
    },
    {
      "id": "35a",
      "section_id": 9,
      "question_text": "What are some of the potential risks associated with this type of business?",
      "question_type": "long_text",
      "priority": 1,
      "depends_on": null,
      "helper_text": "Tech sector volatility, project delays, scope creep, burnout, technology obsolescence"
    },
    {
      "id": "35b",
      "section_id": 9,
      "question_text": "How will you attempt to address/prevent these risks?",
      "question_type": "long_text",
      "priority": 1,
      "depends_on": null,
      "helper_text": "Risk mitigation: diverse client base, contracts, continuous learning, boundaries, insurance"
    }
  ],
  "business_directions": [
    {
      "name": "Technical Consulting",
      "description": "Consulting services leveraging your technical expertise. Set your rates, choose your clients."
    },
    {
      "name": "Content Creation",
      "description": "Thought leadership through blogging, courses, or media. Build an audience around your expertise."
    }
  ]
}
